examples/__init__.py
examples/example.py
examples/get_all_tags.py
examples/get_random_question.py
examples/get_totals_per_tag.py
tests/__init__.py
tests/test_categories.py
tests/test_client.py
tests/test_difficulties.py
tests/test_exceptions.py
tests/test_order.py
tests/test_region.py
tests/test_tags.py
tests/test_types.py
the_trivia_api_library/__init__.py
the_trivia_api_library/categories.py
the_trivia_api_library/client.py
the_trivia_api_library/difficulties.py
the_trivia_api_library/excepts.py
the_trivia_api_library/order.py
the_trivia_api_library/region.py
the_trivia_api_library/tags.py
the_trivia_api_library/types.py
the_trivia_api_library/enums/__init__.py
the_trivia_api_library/enums/enum_category.py
the_trivia_api_library/enums/enum_difficulty.py
the_trivia_api_library/enums/enum_order.py
the_trivia_api_library/enums/enum_type_question.py
the_trivia_api_library-0.0.5.dist-info/licenses/LICENSE
the_trivia_api_library-0.0.5.dist-info/METADATA
the_trivia_api_library-0.0.5.dist-info/WHEEL
the_trivia_api_library-0.0.5.dist-info/top_level.txt
the_trivia_api_library-0.0.5.dist-info/RECORD
